BaseLogn/Log.py
BaseLogn/__init__.py
BaseLogn-1.0.0.dist-info/METADATA
BaseLogn-1.0.0.dist-info/WHEEL
BaseLogn-1.0.0.dist-info/top_level.txt
BaseLogn-1.0.0.dist-info/RECORD
